teleboost/__init__.py
teleboost/__main__.py
teleboost/cli/__init__.py
teleboost/cli/view.py
teleboost/misc.py
teleboost/models.py
teleboost/utils.py
teleboost/view.py
teleboost-0.1.2.dist-info/LICENSE
teleboost-0.1.2.dist-info/WHEEL
teleboost-0.1.2.dist-info/METADATA
teleboost-0.1.2.dist-info/RECORD
