Metadata-Version: 2.1
Name: teleboost
Version: 0.1.2
Summary: Boost Telegram views only using proxies
Author: crinny
Requires-Python: >=3.6,<4.0
Classifier: Programming Language :: Python :: 3
Classifier: Programming Language :: Python :: 3.6
Classifier: Programming Language :: Python :: 3.7
Classifier: Programming Language :: Python :: 3.8
Requires-Dist: aiohttp (>=3.6.2,<4.0.0)
Requires-Dist: aiosocksy (>=0.1.2,<0.2.0)
Requires-Dist: cleo (>=0.8.1,<0.9.0)
Requires-Dist: pydantic (>=1.5.1,<2.0.0)
Requires-Dist: random_user_agent (>=1.0.1,<2.0.0)
Requires-Dist: yaspin (>=0.17.0,<0.18.0)
